README.md
setup.py
im2ascii/__init__.py
im2ascii.egg-info/PKG-INFO
im2ascii.egg-info/SOURCES.txt
im2ascii.egg-info/dependency_links.txt
im2ascii.egg-info/top_level.txt