Metadata-Version: 2.1
Name: im2ascii
Version: 0.0.1
Summary: Display your images in form of ascii typed characters!
Home-page: https://github.com/rrayes3110/Im2ascii
Author: Rafael Rayes
Author-email: rafa@rayes.com.br
License: UNKNOWN
Platform: UNKNOWN
Classifier: Programming Language :: Python :: 3
Classifier: License :: OSI Approved :: MIT License
Classifier: Operating System :: OS Independent
